sshuserclient/__init__.py
sshuserclient/client.py
sshuserclient/config.py
sshuserclient-0.3.dist-info/DESCRIPTION.rst
sshuserclient-0.3.dist-info/METADATA
sshuserclient-0.3.dist-info/RECORD
sshuserclient-0.3.dist-info/WHEEL
sshuserclient-0.3.dist-info/metadata.json
sshuserclient-0.3.dist-info/top_level.txt
